pysercomb/__init__.py
pysercomb/exceptions.py
pysercomb/parsing.py
pysercomb/parsing_parsec.py
pysercomb/types.py
pysercomb/utils.py
pysercomb/parsers/__init__.py
pysercomb/parsers/pax.py
pysercomb/parsers/racket.py
pysercomb/parsers/units.py
pysercomb/pyr/__init__.py
pysercomb/pyr/core.py
pysercomb/pyr/pyr_units.txt
pysercomb/pyr/types.py
pysercomb/pyr/units.py
pysercomb-0.0.14.dist-info/licenses/LICENSE
pysercomb-0.0.14.dist-info/METADATA
pysercomb-0.0.14.dist-info/WHEEL
pysercomb-0.0.14.dist-info/top_level.txt
pysercomb-0.0.14.dist-info/RECORD
