Metadata-Version: 2.4
Name: pysercomb
Version: 0.0.14
Summary: parser combinator library and assorted parsers
Home-page: https://github.com/tgbugs/parsercomb
Author: Tom Gillespie
Author-email: tgbugs@gmail.com
License: MIT
Keywords: python parsing parser combinator scientific units parsec protc
Classifier: Development Status :: 4 - Beta
Classifier: License :: OSI Approved :: MIT License
Classifier: Programming Language :: Python :: 3.6
Classifier: Programming Language :: Python :: 3.7
Classifier: Programming Language :: Python :: 3.8
Classifier: Programming Language :: Python :: 3.9
Classifier: Programming Language :: Python :: 3.10
Classifier: Programming Language :: Python :: 3.11
Classifier: Programming Language :: Python :: Implementation :: CPython
Classifier: Programming Language :: Python :: Implementation :: PyPy
Classifier: Operating System :: POSIX :: Linux
Classifier: Operating System :: MacOS :: MacOS X
Classifier: Operating System :: Microsoft :: Windows
Requires-Python: >=3.6
License-File: LICENSE
Requires-Dist: pint>=0.16.1
Requires-Dist: uncertainties
Requires-Dist: babel
Provides-Extra: units
Requires-Dist: protcur; extra == "units"
Provides-Extra: rdf
Requires-Dist: pyontutils>=0.1.28; extra == "rdf"
Provides-Extra: test
Requires-Dist: pytest; extra == "test"
Requires-Dist: pyontutils>=0.1.28; extra == "test"
Requires-Dist: protcur; extra == "test"
Dynamic: author
Dynamic: author-email
Dynamic: classifier
Dynamic: description
Dynamic: description-content-type
Dynamic: home-page
Dynamic: keywords
Dynamic: license
Dynamic: license-file
Dynamic: provides-extra
Dynamic: requires-dist
Dynamic: requires-python
Dynamic: summary
